NetCloudAPI
