Metadata-Version: 1.1
Name: netcloudapi
Version: 0.1.2a2
Summary: Python Interface for the Cradlepoint NetCloud API V2
Home-page: https://github.com/anthonyjmartinez/netcloudapi
Author: Anthony Martinez
Author-email: anthony.martinez@gmail.com
License: UNKNOWN
Platform: UNKNOWN
Classifier: License :: OSI Approved :: MIT License
Classifier: Development Status :: 3 - Alpha
Classifier: Environment :: Other Environment
Classifier: Intended Audience :: Developers
Classifier: Intended Audience :: System Administrators
Classifier: Operating System :: OS Independent
Classifier: Programming Language :: Python :: 3
Classifier: Topic :: Software Development :: Libraries :: Python Modules
Classifier: Topic :: System :: Systems Administration
Classifier: Topic :: Utilities
